mumpropagator/__init__.py
mumpropagator/_mumpropagator.cpython-310-darwin.so
mumpropagator/pymum.py
mumpropagator/pymum_example.py
mumpropagator-1.0.4.dist-info/LICENSE
mumpropagator-1.0.4.dist-info/METADATA
mumpropagator-1.0.4.dist-info/WHEEL
mumpropagator-1.0.4.dist-info/top_level.txt
mumpropagator-1.0.4.dist-info/RECORD
