Metadata-Version: 2.1
Name: mumpropagator
Version: 1.0.4
Summary: A python interface to Muon Propagator package MUM, developed by Igor Sokalski
License: MIT
License-File: LICENSE
